zprp_ffmpeg2/__init__.py
zprp_ffmpeg2/_api_compat.py
zprp_ffmpeg2/base_connector.py
zprp_ffmpeg2/filter_graph.py
zprp_ffmpeg2/filters.py
zprp_ffmpeg2/generated_filters.py
zprp_ffmpeg2/probe.py
zprp_ffmpeg2/process_connector.py
zprp_ffmpeg2/py.typed
zprp_ffmpeg2/view.py
zprp_ffmpeg2-3.2.0.dist-info/AUTHORS.rst
zprp_ffmpeg2-3.2.0.dist-info/LICENSE
zprp_ffmpeg2-3.2.0.dist-info/METADATA
zprp_ffmpeg2-3.2.0.dist-info/WHEEL
zprp_ffmpeg2-3.2.0.dist-info/RECORD
