Metadata-Version: 2.3
Name: zprp_ffmpeg2
Version: 3.2.0
Summary: ffmpeg filter graph bindings for python
License: MIT
Author: Gregory Chmielewski
Requires-Python: >=3.8,<4.0
Classifier: License :: OSI Approved :: MIT License
Classifier: Programming Language :: Python :: 3
Classifier: Programming Language :: Python :: 3.8
Classifier: Programming Language :: Python :: 3.9
Classifier: Programming Language :: Python :: 3.10
Classifier: Programming Language :: Python :: 3.11
Classifier: Programming Language :: Python :: 3.12
Classifier: Programming Language :: Python :: 3.13
Requires-Dist: ordered-set (>=4.1.0,<5.0.0)
Requires-Dist: oslex (>=0.1.3,<0.2.0)
Requires-Dist: pycparser (>=2.22,<3.0)
Requires-Dist: pytest (>=8.2.2,<9.0.0)
Requires-Dist: tox (>=4.15.1,<5.0.0)
Requires-Dist: tqdm (>=4.66.4,<5.0.0)
